dim/__init__.py
dim/__main__.py
dim/argparser.py
dim/base.py
dim/buffer.py
dim/command.py
dim/dim.py
dim/editor.py
dim/insert.py
dim/keys.py
dim/position.py
dim/select.py
dim/state.py
dim/debug/HELLO WORLD
dim/debug/LONG LINE
dim/debug/LOREM IPSUM
dim/debug/WIKIPEDIA
dim/tutorial/1679091c5a880faf6fb5e6087eb1b2dc
dim/tutorial/a87ff679a2f3e71d9181a67b7542122c
dim/tutorial/c4ca4238a0b923820dcc509a6f75849b
dim/tutorial/c81e728d9d4c2f636f067f89cc14862c
dim/tutorial/e4da3b7fbbce2345d7772b0674a318d5
dim/tutorial/eccbc87e4b5ce2fe28308fd9f2a7baf3
dim_editor-1.0.1.dist-info/LICENSE
dim_editor-1.0.1.dist-info/METADATA
dim_editor-1.0.1.dist-info/WHEEL
dim_editor-1.0.1.dist-info/entry_points.txt
dim_editor-1.0.1.dist-info/top_level.txt
dim_editor-1.0.1.dist-info/RECORD
