Metadata-Version: 2.1
Name: dim-editor
Version: 1.0.1
Summary: A simple terminal text editor based on Vim
Home-page: https://github.com/BattleMage0231/dim
Author: Leyang Zou
License: UNKNOWN
Platform: UNKNOWN
Classifier: Programming Language :: Python :: 3
Classifier: License :: OSI Approved :: MIT License
Classifier: Operating System :: OS Independent
Requires-Python: >=3.8
Requires-Dist: windows-curses ; sys_platform == "win32"
